.gitignore
README.txt
setup.cfg
setup.py
collective/__init__.py
collective.interfaces.egg-info/PKG-INFO
collective.interfaces.egg-info/SOURCES.txt
collective.interfaces.egg-info/dependency_links.txt
collective.interfaces.egg-info/entry_points.txt
collective.interfaces.egg-info/namespace_packages.txt
collective.interfaces.egg-info/not-zip-safe
collective.interfaces.egg-info/requires.txt
collective.interfaces.egg-info/top_level.txt
collective/interfaces/README.txt
collective/interfaces/__init__.py
collective/interfaces/browser.py
collective/interfaces/configure.zcml
collective/interfaces/interfaces.pt
collective/interfaces/tests.py
collective/interfaces/updatei18n.sh
collective/interfaces/locales/collective.interfaces.pot
collective/interfaces/locales/cs/LC_MESSAGES/collective.interfaces.po
collective/interfaces/locales/en/LC_MESSAGES/collective.interfaces.po
collective/interfaces/locales/fi/LC_MESSAGES/collective.interfaces.po
collective/interfaces/profiles/default/actions.xml
collective/interfaces/profiles/default/browserlayer.xml
collective/interfaces/profiles/default/metadata.xml
docs/HISTORY.txt
docs/INSTALL.txt
docs/LICENSE.GPL
docs/LICENSE.txt