Metadata-Version: 1.1
Name: collective.interfaces
Version: 1.1.2
Summary: Adds interfaces tab to Plone's content where Manager's can manage marker interfaces.
Home-page: http://github.com/collective/collective.interfaces
Author: Lukas Zdych
Author-email: lukas.zdych@gmail.com
License: GPL
Keywords: plone interface ui
Platform: UNKNOWN
Classifier: Framework :: Plone
Classifier: Programming Language :: Python
